pypipelines/__init__.py
pypipelines/src/__init__.py
pypipelines/src/exceptions/__init__.py
pypipelines/src/iterators/__init__.py
tests/__init__.py
tests/main.py
py_pipelines-1.0.3.dist-info/LICENSE
py_pipelines-1.0.3.dist-info/LICENSE.txt
py_pipelines-1.0.3.dist-info/METADATA
py_pipelines-1.0.3.dist-info/WHEEL
py_pipelines-1.0.3.dist-info/top_level.txt
py_pipelines-1.0.3.dist-info/RECORD
