Metadata-Version: 2.1
Name: py-pipelines
Version: 1.0.3
Summary: Function pipelines
Home-page: https://github.com/RiccardoCurcio/py-pipeline.git
Download-URL: https://github.com/RiccardoCurcio/py-pipeline/archive/refs/heads/master.zip
Author: Riccardo Curcio
Author-email: curcioriccardo@gmail.com
License: GPL v3
Keywords: functional,pipeline,async pipeline
Platform: UNKNOWN
Classifier: Programming Language :: Python :: 3
Classifier: License :: OSI Approved :: GNU General Public License v3 (GPLv3)
Classifier: Operating System :: OS Independent
Requires-Python: >=3.10
License-File: LICENSE
License-File: LICENSE.txt
Requires-Dist: typing
